findbook/findbook/__init__.py
findbook/findbook/findbook.py
findbook-0.1.3.dist-info/METADATA
findbook-0.1.3.dist-info/WHEEL
findbook-0.1.3.dist-info/entry_points.txt
findbook-0.1.3.dist-info/top_level.txt
findbook-0.1.3.dist-info/RECORD
