Metadata-Version: 2.1
Name: findbook
Version: 0.1.3
Summary: A command-line tool to search for books on Goodreads.
Home-page: 
Author: DShaarvin
Author-email: domunshaarvin@gmail.com
Classifier: Development Status :: 3 - Alpha
Classifier: Intended Audience :: End Users/Desktop
Classifier: License :: OSI Approved :: MIT License
Classifier: Programming Language :: Python :: 3.8
Requires-Dist: requests (==2.26.0)
Requires-Dist: beautifulsoup4 (==4.9.3)
